{
  "belier": {
    "intro": "下弦の月が山羊座の最終度数で輝く今日、火のエレメントを持つあなたの情熱は新たな形へと結晶化していく。逆行惑星のない澄んだ宇宙の流れが、牡羊座太陽の純粋な推進力を支えている。",
    "love": "感情の潮が引いていく中で、真の絆だけが残る時。表面的な魅力よりも、深い信頼と尊敬に基づく関係が浮き彫りになる。過去の恋愛パターンを手放し、より成熟した愛の形を受け入れる準備が整っている。",
    "work": "山羊座月の影響で、あなたの衝動的な性質が建設的な方向へと導かれる。野心的なプロジェクトに実用的なアプローチを取ることで、長期的な成功の基盤を築ける。リーダーシップを発揮しながらも、チームワークの価値を認識する日。",
    "energy": "火星の子であるあなたのバイタリティは、今日は持続力という形で現れる。短距離走者から長距離ランナーへの変化を受け入れ、エネルギーを賢く配分することで一日を通して活力を保てる。",
    "intuition": "月が山羊座の境界線上にある今、あなたの直感は実現可能な夢と非現実的な幻想を見分ける鋭さを持つ。内なる声に耳を傾けながらも、地に足をつけた判断を下すことができる。",
    "luckyNumber": 29,
    "color": "深紅",
    "mantra": "私の情熱は賢明な行動となって現れる",
    "sign": "Bélier",
    "slug": "belier",
    "date": "2026-04-11",
    "author": "Sibylle"
  },
  "taureau": {
    "intro": "下弦の月が山羊座の最終度数で輝く中、牡羊座の太陽があなたの内なる基盤を照らしています。すべての惑星が順行する珍しい宇宙の調和の中で、あなたの金星が支配する感性に新鮮な創造力が流れ込んでいます。",
    "love": "情熱的な牡羊座のエネルギーが、あなたの愛への慎重なアプローチを優しく刺激しています。今日は言葉よりも、小さな思いやりの行動で愛を表現する日。パートナーや大切な人との間に、静かで深い理解が芽生えるでしょう。",
    "work": "山羊座の月の実用的な知恵が、あなたの天性の忍耐力と美しく調和しています。長期的なプロジェクトに集中するのに最適な日で、細部への注意が予想以上の成果をもたらします。金星の恵みで、協力関係も順調に発展するでしょう。",
    "energy": "地のエレメント同士の共鳴により、あなたの体は安定した力強いエネルギーに満たされています。今日は急がず、自然なリズムで動くことで、持続可能な活力を維持できるでしょう。",
    "intuition": "下弦の月が手放しの時を告げる中、直感は古いパターンから解放される道を示しています。静寂の瞬間に耳を傾ければ、心の奥深くから湧き上がる新しい可能性の声が聞こえるはずです。",
    "luckyNumber": 14,
    "color": "深緑",
    "mantra": "私は大地の力と共に、着実に美しい現実を築く",
    "sign": "Taureau",
    "slug": "taureau",
    "date": "2026-04-11",
    "author": "Sibylle"
  },
  "gemeaux": {
    "intro": "下弦の月が山羊座の最終度数で輝く中、あなたの知的好奇心が新たな境地へと導かれます。太陽が牡羊座で力強く燃える今日、あなたの双子座的な軽やかさに情熱的な推進力が加わります。",
    "love": "コミュニケーションが愛の扉を開く鍵となります。言葉の選び方一つで相手の心に深く響き、新しい理解が生まれるでしょう。既存の関係では、率直な対話が絆を強化します。",
    "work": "複数のプロジェクトを同時進行する才能が光ります。山羊座の月の影響で、普段の軽快さに実用的な視点が加わり、効率的な成果を生み出します。新しいアイデアを形にする絶好の機会です。",
    "energy": "身体は軽やかさと集中力のバランスを求めています。短時間の集中作業と適度な休息を繰り返すリズムが、あなたの活力を最大限に引き出すでしょう。",
    "intuition": "直感が言葉として現れやすい一日です。ふとした会話や読書の中に、重要なインスピレーションが隠れているので、心を開いて受け取りましょう。",
    "luckyNumber": 17,
    "color": "明るい黄緑",
    "mantra": "軽やかな心で深い智慧を受け取ります",
    "sign": "Gémeaux",
    "slug": "gemeaux",
    "date": "2026-04-11",
    "author": "Sibylle"
  },
  "cancer": {
    "intro": "下弦の月があなたの支配星として山羊座の最終度数で輝き、手放しと再構築の時を告げています。牡羊座の太陽が新たな始まりのエネルギーを送る中、あなたの感情的な知恵が試されています。",
    "love": "心の奥底に眠る真実が、静かな水面に浮かび上がってきます。過去の感情的なパターンを見直し、愛する人との間に新しい理解の橋を架ける時です。言葉よりも、あなたの直感的な思いやりが相手の心に深く響くでしょう。",
    "work": "実用的なアプローチと創造的な直感のバランスが、今日の成功の鍵となります。山羊座の影響で、責任感と組織力が高まり、長期的なプロジェクトに具体的な進展をもたらします。感情的な洞察を仕事に活かすことで、チームとの結束も深まります。",
    "energy": "月の満ち欠けと共に、あなたのエネルギーも自然な波を描いています。今日は無理をせず、体が求める休息を大切にしてください。",
    "intuition": "あなたの内なる声が、これまでにない明瞭さで響いています。水のエレメントが持つ流動性と、土のエレメントの安定性が融合し、深い洞察へと導かれるでしょう。",
    "luckyNumber": 7,
    "color": "月光の銀",
    "mantra": "流れに身を任せ、心の声を信じて歩む",
    "sign": "Cancer",
    "slug": "cancer",
    "date": "2026-04-11",
    "author": "Sibylle"
  },
  "lion": {
    "intro": "下弦の月が山羊座の最終度数で輝く中、あなたの支配星である太陽が牡羊座を力強く進んでいます。すべての惑星が順行している今、宇宙は純粋な前進のエネルギーをあなたに贈っています。",
    "love": "山羊座の月があなたの愛情表現に深みと責任感をもたらします。軽やかな言葉よりも、具体的な行動で愛を示す時です。パートナーや大切な人との関係において、真の信頼を築く基盤が見えてきます。",
    "work": "太陽が牡羊座で燃える今日、あなたの創造力は新しい領域を開拓する準備ができています。山羊座の月が実用的な視点をもたらし、壮大なビジョンを現実的な計画へと変換させます。リーダーシップを発揮する絶好の機会です。",
    "energy": "火のエレメントが全開で、あなたの生命力は朝日のように輝いています。ただし下弦の月が適度な休息の重要性を示唆しているので、エネルギーを賢く配分することが鍵となります。",
    "intuition": "直感と現実的思考が見事に調和する一日です。心の奥底から湧き上がる知恵に耳を傾けながら、地に足をつけた判断を下せるでしょう。",
    "luckyNumber": 8,
    "color": "黄金色",
    "mantra": "私は太陽のように輝き、大地のように安定している",
    "sign": "Lion",
    "slug": "lion",
    "date": "2026-04-11",
    "author": "Sibylle"
  },
  "vierge": {
    "intro": "下弦の月が山羊座の最終度数で輝く中、あなたの支配星水星が順行の力強さで地の要素に深い安定をもたらします。牡羊座の太陽があなたの実用性と新しい始まりへの意欲を調和させています。",
    "love": "感情の整理整頓が愛を深める鍵となる一日です。相手の本質を見抜く洞察力が冴え、表面的な言葉ではなく真意を読み取れるでしょう。誠実な対話が絆を強固にします。",
    "work": "細部への注意力が成果を左右する時です。山羊座月の影響で、長期的な目標に向けた地道な作業が実を結び始めます。完璧主義を適度に抑えながら、質の高い仕事に集中しましょう。",
    "energy": "身体のメンテナンスに意識を向ける絶好のタイミングです。規則正しいリズムがあなたの生命力を安定させ、持続可能なエネルギーを生み出します。",
    "intuition": "論理と直感が美しく融合する一日となるでしょう。データと感覚の両方を信頼することで、より深い真実に到達できます。",
    "luckyNumber": 14,
    "color": "深緑",
    "mantra": "完璧さの中に美しさを見つける",
    "sign": "Vierge",
    "slug": "vierge",
    "date": "2026-04-11",
    "author": "Sibylle"
  },
  "balance": {
    "intro": "山羊座の最終度数に宿る下弦の月が、あなたの内なる構造を再編成しています。牡羊座の太陽があなたの対向に輝く中、金星に導かれたあなたのバランス感覚が新しい調和を模索しています。",
    "love": "パートナーシップにおいて、与えることと受け取ることの新しいバランスが見えてきます。相手の情熱的なエネルギーを受け入れながら、あなた自身の美的センスを表現する時です。対話を通じて、より深い理解が生まれるでしょう。",
    "work": "プロジェクトや交渉において、あなたの外交的才能が光を放ちます。異なる意見を統合し、全員が納得できる解決策を見つける能力が評価されます。協力関係から生まれる創造的なアイデアに注目してください。",
    "energy": "金星の恵みを受けて、あなたの身体はしなやかな強さを取り戻しています。美しい環境に身を置くことで、エネルギーが自然に回復するでしょう。",
    "intuition": "山羊座の月があなたに実用的な知恵をささやいています。表面的な美しさの奥に隠された真実を見抜く直感が冴えています。",
    "luckyNumber": 7,
    "color": "ローズゴールド",
    "mantra": "調和の中で真の美しさを見つける",
    "sign": "Balance",
    "slug": "balance",
    "date": "2026-04-11",
    "author": "Sibylle"
  },
  "scorpion": {
    "intro": "下弦の月が山羊座の最終度で輝く今日、蠍座のあなたには変容の深い流れが訪れます。牡羊座の太陽があなたの内なる炎を照らし、どの惑星も逆行していない宇宙は、前進への明確な道筋を示しています。",
    "love": "感情の奥深くで静かな革命が起こっています。過去の傷を手放し、真の親密さへの扉を開く時です。パートナーとの間に新しい理解の橋が架かり、一人の場合は自己愛の種が芽吹きます。",
    "work": "山羊座の月があなたのキャリアセクターを照らし、長期的な目標への集中力が高まります。困難なプロジェクトも、今日のあなたなら蠍座特有の粘り強さで突破できるでしょう。権威ある人物からの支援が期待できます。",
    "energy": "水のエレメントが火の太陽と調和し、あなたの生命力は静かながら力強く流れています。激しい活動よりも、深い呼吸とともに内なる力を蓄える日です。",
    "intuition": "冥王星の導きにより、隠された真実を見抜く洞察力が研ぎ澄まされています。直感の声に従い、表面的な現象の奥にある本質を捉えてください。",
    "luckyNumber": 8,
    "color": "深海の紺青",
    "mantra": "私は変容の力を受け入れ、真実の光を見つける",
    "sign": "Scorpion",
    "slug": "scorpion",
    "date": "2026-04-11",
    "author": "Sibylle"
  },
  "sagittaire": {
    "intro": "下弦の月が山羊座の最終度数で輝く中、火のエレメントを持つあなたの内なる冒険心が新たな地平を求めています。木星の子として、この宇宙の調和は責任ある拡張への道筋を示しています。",
    "love": "心の対話において、深い信頼の基盤を築く時です。表面的な会話を超えて、相手の本質を理解しようとする姿勢が、関係に新たな次元をもたらします。誠実さという弓矢で、愛の的の中心を射抜いてください。",
    "work": "プロジェクトの完成に向けて、最後の登攀が始まります。山羊座の月が教えるように、一歩一歩の積み重ねこそが頂上への確実な道です。あなたの哲学的な視点が、チーム全体に新しい可能性を見せるでしょう。",
    "energy": "身体は地に足をつけた行動を求めています。散歩や軽い運動で、大地のエネルギーを取り込みましょう。",
    "intuition": "内なる賢者の声が、人生の次なる章について囁いています。静寂の中で、その導きに耳を傾けてください。",
    "luckyNumber": 9,
    "color": "深緑",
    "mantra": "智慧の光が私の道を照らし、真実への扉を開く",
    "sign": "Sagittaire",
    "slug": "sagittaire",
    "date": "2026-04-11",
    "author": "Sibylle"
  },
  "capricorne": {
    "intro": "月があなたの星座の最後の度数で下弦を迎える今日、山羊座のあなたは一つの章の終わりと新しい始まりの境界に立っています。牡羊座の太陽が力強く輝く中、どの惑星も逆行していない宇宙は、前進への明確な道筋を示しています。",
    "love": "感情の潮が引いていく下弦月は、関係における不要な執着を手放す絶好の機会を与えます。真の愛は、握りしめるのではなく信頼することで深まることを、今日のエネルギーが優しく教えてくれるでしょう。",
    "work": "土星の子として、あなたは建設的な変化を恐れません。今日は長期プロジェクトの見直しや、より効率的なシステムの導入に最適な日です。牡羊座の火のエネルギーが、あなたの慎重な計画に勇敢な行動力を加えます。",
    "energy": "下弦月の静寂なエネルギーが、あなたの内なる電池を静かに充電しています。急がず、自然のリズムに身を委ねることで、持続可能な活力を得られるでしょう。",
    "intuition": "月があなたの星座を離れる前の最後の囁きに耳を傾けてください。直感は、論理的な思考の隙間から現れる微細な知恵として訪れます。",
    "luckyNumber": 29,
    "color": "深緑",
    "mantra": "手放すことで、新しい可能性が生まれる",
    "sign": "Capricorne",
    "slug": "capricorne",
    "date": "2026-04-11",
    "author": "Sibylle"
  },
  "verseau": {
    "intro": "山羊座の下弦の月が古い構造への執着を手放すよう促し、牡羊座の太陽があなたの革新的な精神に新たな始まりの炎を灯しています。どの惑星も逆行していない今、宇宙はあなたの前進への道を清めています。",
    "love": "感情的な壁を築く代わりに、真の親密さへの橋を架ける時です。パートナーや愛する人との関係で、古いパターンを手放し、より自由で平等な絆を育みましょう。",
    "work": "伝統的な手法に固執せず、あなた独自のアプローチを信頼してください。チームの中で変革の触媒となり、新しいアイデアを具体的な行動に変える力があります。",
    "energy": "風のエレメントがあなたの内なる活力を高め、心身ともに軽やかさを感じるでしょう。新鮮な空気を求める体の声に従い、屋外での活動を取り入れてください。",
    "intuition": "天王星からの電流のような閃きが、予期せぬ洞察をもたらします。直感が論理を超越する瞬間を大切にし、内なる革命家の声に耳を傾けてください。",
    "luckyNumber": 11,
    "color": "電気青",
    "mantra": "私は変化の風となり、新しい可能性を世界に運ぶ",
    "sign": "Verseau",
    "slug": "verseau",
    "date": "2026-04-11",
    "author": "Sibylle"
  },
  "poissons": {
    "intro": "山羊座の月が最後の度数で輝き、牡羊座の太陽があなたの内なる炎を呼び覚ます。逆行する惑星がない今日、宇宙は前進への明確な道を示している。",
    "love": "感情の深い海から、実用的な愛の表現へと舵を切る時。言葉よりも行動で、夢よりも具体的な計画で愛を育もう。パートナーシップに新たな構造を築く絶好の機会が訪れる。",
    "work": "創造性と実務の完璧な融合が可能な日。あなたの直感的なアイデアを、山羊座の月の堅実なエネルギーが形にしてくれる。長期的なビジョンを現実的なステップに分解して進めよう。",
    "energy": "春の活力が血管を駆け巡り、冬の重さが軽やかに解けていく。水のエレメントがあなたに柔軟性を与え、疲れを癒しの流れに変える。",
    "intuition": "ネプチューンの霧が晴れ、今日のあなたの直感は水晶のように透明。内なる声は山羊座の実用的な知恵と調和し、確実な導きを与えてくれる。",
    "luckyNumber": 11,
    "color": "深海の緑青",
    "mantra": "流れに身を任せながらも、しっかりと根を張る",
    "sign": "Poissons",
    "slug": "poissons",
    "date": "2026-04-11",
    "author": "Sibylle"
  }
}